<?xml version="1.0"?>
<contacts>
  <!--   USUÁRIOS DESLIGADOS
<contact name="NAYARA SILVA " number="3042" firstname="" lastname="" phone="" mobile="" email="" address="" city="" state="" zip="" comment="" id="" info="Not online" presence="1" directory="1"/>
<contact name="ELIZETE FONSECA " number="3012" firstname="" lastname="" phone="" mobile="" email="" address="" city="" state="" zip="" comment="" id="" info="Ready" presence="1" directory="1"/>
<contact name="ISABELA MELO " number="3097" firstname="" lastname="" phone="" mobile="" email="" address="" city="" state="" zip="" comment="" id="" info="Not online" presence="1" directory="1"/>
<contact name="LIGIA FERNANDES " number="3030" firstname="" lastname="" phone="" mobile="" email="" address="" city="" state="" zip="" comment="" id="" info="Ready" presence="1" directory="1"/>
<contact name="TOM KELVE " number="3076" firstname="" lastname="" phone="" mobile="" email="" address="" city="" state="" zip="" comment="" id="" info="Ready" presence="1" directory="1"/>
<contact name="DANIEL COSTA " number="3026" firstname="" lastname="" phone="" mobile="" email="" address="" city="" state="" zip="" comment="" id="" info="Ready" presence="1" directory="1"/>
<contact name="DAVI PEDROZA " number="3085" firstname="" lastname="" phone="" mobile="" email="" address="" city="" state="" zip="" comment="" id="" info="Not online" presence="1" directory="1"/>
<contact name="LUANA CARMELITA " number="3015" firstname="" lastname="" phone="" mobile="" email="" address="" city="" state="" zip="" comment="" id="" info="Not online" presence="1" directory="1"/>
<contact name="SARAH SILVA" number="3028" firstname="" lastname="" phone="" mobile="" email="" address="" city="" state="" zip="" comment="" id="" info="Not online" presence="1" directory="1"/>
<contact name="ANDERSON PINHEIRO " number="7082" firstname="" lastname="" phone="" mobile="" email="" address="" city="" state="" zip="" comment="" id="" info="Not online" presence="1" directory="1"/>
<contact name="BRUNA LEITE " number="3034" firstname="" lastname="" phone="" mobile="" email="" address="" city="" state="" zip="" comment="" id="" info="Ready" presence="1" directory="1"/>
<contact name="BRUNO FREITAS " number="3075" firstname="" lastname="" phone="" mobile="" email="" address="" city="" state="" zip="" comment="" id="" info="Ready" presence="1" directory="1"/>
<contact name="EBERTH OLIVEIRA " number="3069" firstname="" lastname="" phone="" mobile="" email="" address="" city="" state="" zip="" comment="" id="" info="Ready" presence="1" directory="1"/>
<contact name="ELIANA SILVA " number="3058" firstname="" lastname="" phone="" mobile="" email="" address="" city="" state="" zip="" comment="" id="" info="Ready" presence="1" directory="1"/>
<contact name="ELISABETE TORRES " number="3126" firstname="" lastname="" phone="" mobile="" email="" address="" city="" state="" zip="" comment="" id="" info="Not online" presence="1" directory="1"/>
<contact name="LARISSA MOURA " number="3132" firstname="" lastname="" phone="" mobile="" email="" address="" city="" state="" zip="" comment="" id="" info="Not online" presence="1" directory="1"/>
<contact name="RUTH SOUZA " number="3048" firstname="" lastname="" phone="" mobile="" email="" address="" city="" state="" zip="" comment="" id="" info="Ready" presence="1" directory="1"/>
<contact name="LUNNARA ALVES " number="3062" firstname="" lastname="" phone="" mobile="" email="" address="" city="" state="" zip="" comment="" id="" info="Not online" presence="1" directory="1"/>
<contact name="DEYVIDE OLIVEIRA " number="3057" firstname="" lastname="" phone="" mobile="" email="" address="" city="" state="" zip="" comment="" id="" info="Ready" presence="1" directory="1"/>

-->

<contact name="*VD TOUROS " number="4048" firstname="" lastname="" phone="" mobile="" email="" address="" city="" state="" zip="" comment="" id="" info="Ready" presence="1" directory="1"/>
<contact name="*LV TOUROS " number="4047" firstname="" lastname="" phone="" mobile="" email="" address="" city="" state="" zip="" comment="" id="" info="Ready" presence="1" directory="1"/>
<contact name="JOYCE OLIVEIRA " number="3092" firstname="" lastname="" phone="" mobile="" email="" address="" city="" state="" zip="" comment="" id="" info="Ready" presence="1" directory="1"/>       
<contact name="AGENTE MONITORAMENTO " number="3079" firstname="" lastname="" phone="" mobile="" email="" address="" city="" state="" zip="" comment="" id="" info="Ready" presence="1" directory="1"/>       
<contact name="*VD MACAU " number="4046" firstname="" lastname="" phone="" mobile="" email="" address="" city="" state="" zip="" comment="" id="" info="Ready" presence="1" directory="1"/>     
<contact name="*LV MACAU " number="4045" firstname="" lastname="" phone="" mobile="" email="" address="" city="" state="" zip="" comment="" id="" info="Ready" presence="1" directory="1"/>     
<contact name="*LV FERREIRA COSTA " number="4044" firstname="" lastname="" phone="" mobile="" email="" address="" city="" state="" zip="" comment="" id="" info="Ready" presence="1" directory="1"/>   
<contact name="*VD LAGOA SECA " number="5012" firstname="" lastname="" phone="" mobile="" email="" address="" city="" state="" zip="" comment="" id="" info="Ready" presence="1" directory="1"/>      
<contact name="*LV LAGOA SECA " number="5011" firstname="" lastname="" phone="" mobile="" email="" address="" city="" state="" zip="" comment="" id="" info="Ready" presence="1" directory="1"/>      
<contact name="*LV CEARA MIRIM " number="4042" firstname="" lastname="" phone="" mobile="" email="" address="" city="" state="" zip="" comment="" id="" info="Ready" presence="1" directory="1"/>      
<contact name="*VD CEARA MIRIM " number="4043" firstname="" lastname="" phone="" mobile="" email="" address="" city="" state="" zip="" comment="" id="" info="Ready" presence="1" directory="1"/>    
<contact name="*LV ANJO DA GUARDA " number="7026" firstname="" lastname="" phone="" mobile="" email="" address="" city="" state="" zip="" comment="" id="" info="Not online" presence="1" directory="1"/>
<contact name="*LV CARREFOUR " number="4008" firstname="" lastname="" phone="" mobile="" email="" address="" city="" state="" zip="" comment="" id="" info="Ready" presence="1" directory="1"/>
<contact name="*LV CARUTAPERA " number="7032" firstname="" lastname="" phone="" mobile="" email="" address="" city="" state="" zip="" comment="" id="" info="Not online" presence="1" directory="1"/>
<contact name="*LV CCAB " number="4007" firstname="" lastname="" phone="" mobile="" email="" address="" city="" state="" zip="" comment="" id="" info="Ready" presence="1" directory="1"/>
<contact name="*LV CENTRO MOSSORO " number="4028" firstname="" lastname="" phone="" mobile="" email="" address="" city="" state="" zip="" comment="" id="" info="Ready" presence="1" directory="1"/>
<contact name="*LV CENTRO NATAL " number="4005" firstname="" lastname="" phone="" mobile="" email="" address="" city="" state="" zip="" comment="" id="" info="Ready" presence="1" directory="1"/>
<contact name="*LV CIDADE ALTERNATIVO " number="4027" firstname="" lastname="" phone="" mobile="" email="" address="" city="" state="" zip="" comment="" id="" info="Ready" presence="1" directory="1"/>
<contact name="*LV CIDADE ATACADAO " number="4011" firstname="" lastname="" phone="" mobile="" email="" address="" city="" state="" zip="" comment="" id="" info="Ready" presence="1" directory="1"/>
<contact name="*LV CIDADE JARDIM " number="4003" firstname="" lastname="" phone="" mobile="" email="" address="" city="" state="" zip="" comment="" id="" info="Ready" presence="1" directory="1"/>
<contact name="*LV CIDADE OPERARIA " number="7013" firstname="" lastname="" phone="" mobile="" email="" address="" city="" state="" zip="" comment="" id="" info="Ready" presence="1" directory="1"/>
<contact name="*LV COHAB " number="7005" firstname="" lastname="" phone="" mobile="" email="" address="" city="" state="" zip="" comment="" id="" info="Ready" presence="1" directory="1"/>
<contact name="*LV COHATRAC " number="7004" firstname="" lastname="" phone="" mobile="" email="" address="" city="" state="" zip="" comment="" id="" info="Ready" presence="1" directory="1"/>
<contact name="*LV CONTEINER SANTA INÊS " number="7039" firstname="" lastname="" phone="" mobile="" email="" address="" city="" state="" zip="" comment="" id="" info="Ready" presence="1" directory="1"/>
<contact name="*LV CURVA DO 90 " number="7001" firstname="" lastname="" phone="" mobile="" email="" address="" city="" state="" zip="" comment="" id="" info="Not online" presence="1" directory="1"/>
<contact name="*LV EXTREMOZ " number="4037" firstname="" lastname="" phone="" mobile="" email="" address="" city="" state="" zip="" comment="" id="" info="Ready" presence="1" directory="1"/>
<contact name="*LV GOVERNADOR NUNES FREIRE " number="7033" firstname="" lastname="" phone="" mobile="" email="" address="" city="" state="" zip="" comment="" id="" info="Not online" presence="1" directory="1"/>
<contact name="*LV GUAJAJARAS " number="7006" firstname="" lastname="" phone="" mobile="" email="" address="" city="" state="" zip="" comment="" id="" info="Ready" presence="1" directory="1"/>
<contact name="*LV HIPER MOSSORO " number="4024" firstname="" lastname="" phone="" mobile="" email="" address="" city="" state="" zip="" comment="" id="" info="Ready" presence="1" directory="1"/>
<contact name="*LV HIPER SAO LUIS " number="7012" firstname="" lastname="" phone="" mobile="" email="" address="" city="" state="" zip="" comment="" id="" info="Not online" presence="1" directory="1"/>
<contact name="*LV IGAPO " number="4015" firstname="" lastname="" phone="" mobile="" email="" address="" city="" state="" zip="" comment="" id="" info="Ready" presence="1" directory="1"/>
<contact name="*LV JOAO PAULO " number="7009" firstname="" lastname="" phone="" mobile="" email="" address="" city="" state="" zip="" comment="" id="" info="Not online" presence="1" directory="1"/>
<contact name="*LV LUIZA MOTTA " number="5003" firstname="" lastname="" phone="" mobile="" email="" address="" city="" state="" zip="" comment="" id="" info="Ready" presence="1" directory="1"/>
<contact name="*LV MACIEL PINHEIRO " number="5007" firstname="" lastname="" phone="" mobile="" email="" address="" city="" state="" zip="" comment="" id="" info="Ready" presence="1" directory="1"/>
<contact name="*LV MALVINAS " number="5001" firstname="" lastname="" phone="" mobile="" email="" address="" city="" state="" zip="" comment="" id="" info="Ready" presence="1" directory="1"/>
<contact name="*LV MARACACUME " number="7034" firstname="" lastname="" phone="" mobile="" email="" address="" city="" state="" zip="" comment="" id="" info="Ready" presence="1" directory="1"/>
<contact name="*LV MARIA LACERDA " number="4023" firstname="" lastname="" phone="" mobile="" email="" address="" city="" state="" zip="" comment="" id="" info="Ready" presence="1" directory="1"/>
<contact name="*LV MATEUS COHAMA " number="7020" firstname="" lastname="" phone="" mobile="" email="" address="" city="" state="" zip="" comment="" id="" info="Ready" presence="1" directory="1"/>
<contact name="*LV MAXXI ATACADO " number="4040" firstname="" lastname="" phone="" mobile="" email="" address="" city="" state="" zip="" comment="" id="" info="Ready" presence="1" directory="1"/>
<contact name="*LV MIDWAY L1 " number="4014" firstname="" lastname="" phone="" mobile="" email="" address="" city="" state="" zip="" comment="" id="" info="Ready" presence="1" directory="1"/>
<contact name="*LV MIDWAY L3 " number="4016" firstname="" lastname="" phone="" mobile="" email="" address="" city="" state="" zip="" comment="" id="" info="Ready" presence="1" directory="1"/>
<contact name="*LV NATAL SHOPPING " number="4002" firstname="" lastname="" phone="" mobile="" email="" address="" city="" state="" zip="" comment="" id="" info="Ready" presence="1" directory="1"/>
<contact name="*LV NORDESTAO PONTA NEGRA " number="4019" firstname="" lastname="" phone="" mobile="" email="" address="" city="" state="" zip="" comment="" id="" info="Ready" presence="1" directory="1"/>
<contact name="*LV NORTE SHOPPING " number="4010" firstname="" lastname="" phone="" mobile="" email="" address="" city="" state="" zip="" comment="" id="" info="Ready" presence="1" directory="1"/>
<contact name="*LV PARACURU " number="6005" firstname="" lastname="" phone="" mobile="" email="" address="" city="" state="" zip="" comment="" id="" info="Ready" presence="1" directory="1"/>
<contact name="*LV PARAIPABA " number="6011" firstname="" lastname="" phone="" mobile="" email="" address="" city="" state="" zip="" comment="" id="" info="Ready" presence="1" directory="1"/>
<contact name="*LV PARNAMIRIM " number="4001" firstname="" lastname="" phone="" mobile="" email="" address="" city="" state="" zip="" comment="" id="" info="Ready" presence="1" directory="1"/>
<contact name="*LV PARTAGE CAMPINA GRANDE " number="5005" firstname="" lastname="" phone="" mobile="" email="" address="" city="" state="" zip="" comment="" id="" info="Ready" presence="1" directory="1"/>
<contact name="*LV PARTAGE MOSSORO " number="4025" firstname="" lastname="" phone="" mobile="" email="" address="" city="" state="" zip="" comment="" id="" info="Ready" presence="1" directory="1"/>
<contact name="*LV SHOPPING PASSEIO " number="7015" firstname="" lastname="" phone="" mobile="" email="" address="" city="" state="" zip="" comment="" id="" info="Ready" presence="1" directory="1"/>
<contact name="*LV PECEM " number="6002" firstname="" lastname="" phone="" mobile="" email="" address="" city="" state="" zip="" comment="" id="" info="Ready" presence="1" directory="1"/>
<contact name="*LV PENTECOSTE " number="6003" firstname="" lastname="" phone="" mobile="" email="" address="" city="" state="" zip="" comment="" id="" info="Ready" presence="1" directory="1"/>
<contact name="*LV PINDARE-MIRIM " number="7035" firstname="" lastname="" phone="" mobile="" email="" address="" city="" state="" zip="" comment="" id="" info="Ready" presence="1" directory="1"/>
<contact name="*LV PLANALTO" number="4034" firstname="" lastname="" phone="" mobile="" email="" address="" city="" state="" zip="" comment="" id="" info="Ready" presence="1" directory="1"/>
<contact name="*LV POTENGI" number="4006" firstname="" lastname="" phone="" mobile="" email="" address="" city="" state="" zip="" comment="" id="" info="Ready" presence="1" directory="1"/>
<contact name="*LV PRAIA SHOPPING " number="4009" firstname="" lastname="" phone="" mobile="" email="" address="" city="" state="" zip="" comment="" id="" info="Ready" presence="1" directory="1"/>
<contact name="*LV PATIO NORTE " number="7011" firstname="" lastname="" phone="" mobile="" email="" address="" city="" state="" zip="" comment="" id="" info="Not online" presence="1" directory="1"/>
<contact name="*LV QDB ILHA " number="7040" firstname="" lastname="" phone="" mobile="" email="" address="" city="" state="" zip="" comment="" id="" info="Not online" presence="1" directory="1"/>
<contact name="*LV QDB MIDWAY " number="2001" firstname="" lastname="" phone="" mobile="" email="" address="" city="" state="" zip="" comment="" id="" info="Not online" presence="1" directory="1"/>
<contact name="*LV QUIOSQUE REBOUCAS " number="4026" firstname="" lastname="" phone="" mobile="" email="" address="" city="" state="" zip="" comment="" id="" info="Ready" presence="1" directory="1"/>
<contact name="*LV QUIOSQUE TURU " number="7024" firstname="" lastname="" phone="" mobile="" email="" address="" city="" state="" zip="" comment="" id="" info="Not online" presence="1" directory="1"/>
<contact name="*LV REBOUCAS " number="4018" firstname="" lastname="" phone="" mobile="" email="" address="" city="" state="" zip="" comment="" id="" info="Ready" presence="1" directory="1"/>
<contact name="*LV REDE COMPRAS " number="5006" firstname="" lastname="" phone="" mobile="" email="" address="" city="" state="" zip="" comment="" id="" info="Ready" presence="1" directory="1"/>
<contact name="*LV RIO ANIL " number="7017" firstname="" lastname="" phone="" mobile="" email="" address="" city="" state="" zip="" comment="" id="" info="Not online" presence="1" directory="1"/>
<contact name="*LV CENTRO RIO BRANCO " number="4029" firstname="" lastname="" phone="" mobile="" email="" address="" city="" state="" zip="" comment="" id="" info="Ready" presence="1" directory="1"/>
<contact name="*LV RUA GRANDE II " number="7018" firstname="" lastname="" phone="" mobile="" email="" address="" city="" state="" zip="" comment="" id="" info="Ready" presence="1" directory="1"/>
<contact name="*LV RUA GRANDE I" number="7007" firstname="" lastname="" phone="" mobile="" email="" address="" city="" state="" zip="" comment="" id="" info="Ready" presence="1" directory="1"/>
<contact name="*LV SALGADO FILHO " number="4017" firstname="" lastname="" phone="" mobile="" email="" address="" city="" state="" zip="" comment="" id="" info="Ready" presence="1" directory="1"/>
<contact name="*LV SANTA INES " number="7031" firstname="" lastname="" phone="" mobile="" email="" address="" city="" state="" zip="" comment="" id="" info="Ready" presence="1" directory="1"/>
<contact name="*LV SANTA LUZIA DO PARUA " number="7037" firstname="" lastname="" phone="" mobile="" email="" address="" city="" state="" zip="" comment="" id="" info="Not online" presence="1" directory="1"/>
<contact name="*LV SANTA LUZIA DO TIDE" number="7036" firstname="" lastname="" phone="" mobile="" email="" address="" city="" state="" zip="" comment="" id="" info="Ready" presence="1" directory="1"/>
<contact name="*LV SAO GONCALO DO AMARANTE-CE " number="6007" firstname="" lastname="" phone="" mobile="" email="" address="" city="" state="" zip="" comment="" id="" info="Ready" presence="1" directory="1"/>
<contact name="*LV SHOPPING 10 " number="4012" firstname="" lastname="" phone="" mobile="" email="" address="" city="" state="" zip="" comment="" id="" info="Ready" presence="1" directory="1"/>
<contact name="*LV SHOPPING DA ILHA " number="7019" firstname="" lastname="" phone="" mobile="" email="" address="" city="" state="" zip="" comment="" id="" info="Ready" presence="1" directory="1"/>
<contact name="*LV SHOPPING DO AUTOMOVEL " number="7002" firstname="" lastname="" phone="" mobile="" email="" address="" city="" state="" zip="" comment="" id="" info="Ready" presence="1" directory="1"/>
<contact name="*LV SHOPPING TROPICAL " number="7008" firstname="" lastname="" phone="" mobile="" email="" address="" city="" state="" zip="" comment="" id="" info="Ready" presence="1" directory="1"/>
<contact name="*LV SPICY " number="2013" firstname="" lastname="" phone="" mobile="" email="" address="" city="" state="" zip="" comment="" id="" info="Not online" presence="1" directory="1"/>
<contact name="*LV SUPER FACIL RODOVIARIA " number="4041" firstname="" lastname="" phone="" mobile="" email="" address="" city="" state="" zip="" comment="" id="" info="Ready" presence="1" directory="1"/>
<contact name="*LV SUPERMERCADO CIDADE MOSSORO " number="4022" firstname="" lastname="" phone="" mobile="" email="" address="" city="" state="" zip="" comment="" id="" info="Ready" presence="1" directory="1"/>
<contact name="*LV SUPERMERCADO IDEAL " number="5004" firstname="" lastname="" phone="" mobile="" email="" address="" city="" state="" zip="" comment="" id="" info="Ready" presence="1" directory="1"/>
<contact name="*LV SAO GONÇALO DO AMARANTE-RN " number="4038" firstname="" lastname="" phone="" mobile="" email="" address="" city="" state="" zip="" comment="" id="" info="Ready" presence="1" directory="1"/>
<contact name="*LV SAO LUIS SHOPPING " number="7010" firstname="" lastname="" phone="" mobile="" email="" address="" city="" state="" zip="" comment="" id="" info="Ready" presence="1" directory="1"/>
<contact name="*LV TIROL " number="4013" firstname="" lastname="" phone="" mobile="" email="" address="" city="" state="" zip="" comment="" id="" info="Ready" presence="1" directory="1"/>
<contact name="*LV TRAIRI " number="6009" firstname="" lastname="" phone="" mobile="" email="" address="" city="" state="" zip="" comment="" id="" info="Ready" presence="1" directory="1"/>
<contact name="*LV TO QUE TO " number="4004" firstname="" lastname="" phone="" mobile="" email="" address="" city="" state="" zip="" comment="" id="" info="Ready" presence="1" directory="1"/>
<contact name="*VD CENTRO CG " number="5010" firstname="" lastname="" phone="" mobile="" email="" address="" city="" state="" zip="" comment="" id="" info="Ready" presence="1" directory="1"/>
<contact name="*VD EXTREMOZ " number="4036" firstname="" lastname="" phone="" mobile="" email="" address="" city="" state="" zip="" comment="" id="" info="Ready" presence="1" directory="1"/>
<contact name="*VD KENNEDY " number="7028" firstname="" lastname="" phone="" mobile="" email="" address="" city="" state="" zip="" comment="" id="" info="Ready" presence="1" directory="1"/>
<contact name="*VD MALVINAS " number="5002" firstname="" lastname="" phone="" mobile="" email="" address="" city="" state="" zip="" comment="" id="" info="Ready" presence="1" directory="1"/>
<contact name="*VD MARAJO " number="7029" firstname="" lastname="" phone="" mobile="" email="" address="" city="" state="" zip="" comment="" id="" info="Ready" presence="1" directory="1"/>
<contact name="*VD MOSSORO " number="4033" firstname="" lastname="" phone="" mobile="" email="" address="" city="" state="" zip="" comment="" id="" info="Ready" presence="1" directory="1"/>
<contact name="*VD NORTE SHOPPING " number="4030" firstname="" lastname="" phone="" mobile="" email="" address="" city="" state="" zip="" comment="" id="" info="Ready" presence="1" directory="1"/>
<contact name="*VD PARACURU " number="6006" firstname="" lastname="" phone="" mobile="" email="" address="" city="" state="" zip="" comment="" id="" info="Ready" presence="1" directory="1"/>
<contact name="*VD PARAIPABA " number="6012" firstname="" lastname="" phone="" mobile="" email="" address="" city="" state="" zip="" comment="" id="" info="Ready" presence="1" directory="1"/>
<contact name="*VD PARNAMIRIM " number="4032" firstname="" lastname="" phone="" mobile="" email="" address="" city="" state="" zip="" comment="" id="" info="Ready" presence="1" directory="1"/>
<contact name="*VD PECEM " number="6001" firstname="" lastname="" phone="" mobile="" email="" address="" city="" state="" zip="" comment="" id="" info="Ready" presence="1" directory="1"/>
<contact name="*VD PENTECOSTE " number="6004" firstname="" lastname="" phone="" mobile="" email="" address="" city="" state="" zip="" comment="" id="" info="Ready" presence="1" directory="1"/>
<contact name="*VD PLANALTO " number="4035" firstname="" lastname="" phone="" mobile="" email="" address="" city="" state="" zip="" comment="" id="" info="Ready" presence="1" directory="1"/>
<contact name="*VD SAO GONCALO DO AMARANTE-CE " number="6008" firstname="" lastname="" phone="" mobile="" email="" address="" city="" state="" zip="" comment="" id="" info="Ready" presence="1" directory="1"/>
<contact name="*VD SAO GONCALO DO AMARANTE-RN " number="4039" firstname="" lastname="" phone="" mobile="" email="" address="" city="" state="" zip="" comment="" id="" info="Ready" presence="1" directory="1"/>
<contact name="*VD TRAIRI " number="6010" firstname="" lastname="" phone="" mobile="" email="" address="" city="" state="" zip="" comment="" id="" info="Ready" presence="1" directory="1"/>
<contact name="*VD TURU " number="7030" firstname="" lastname="" phone="" mobile="" email="" address="" city="" state="" zip="" comment="" id="" info="Ready" presence="1" directory="1"/>
<contact name="*VD VIA DIRETA " number="4031" firstname="" lastname="" phone="" mobile="" email="" address="" city="" state="" zip="" comment="" id="" info="Ready" presence="1" directory="1"/>
<contact name="*LV VENANCIO NEIVA " number="5008" firstname="" lastname="" phone="" mobile="" email="" address="" city="" state="" zip="" comment="" id="" info="Ready" presence="1" directory="1"/>
<contact name="*LV VIA DIRETA " number="4021" firstname="" lastname="" phone="" mobile="" email="" address="" city="" state="" zip="" comment="" id="" info="Ready" presence="1" directory="1"/>
<contact name="*LV ZE DOCA " number="7038" firstname="" lastname="" phone="" mobile="" email="" address="" city="" state="" zip="" comment="" id="" info="Not online" presence="1" directory="1"/>
<contact name="ALANIA BATISTA " number="3054" firstname="" lastname="" phone="" mobile="" email="" address="" city="" state="" zip="" comment="" id="" info="Ready" presence="1" directory="1"/>
<contact name="ALEXANDRE CUSTODIO " number="3004" firstname="" lastname="" phone="" mobile="" email="" address="" city="" state="" zip="" comment="" id="" info="Ready" presence="1" directory="1"/>
<contact name="ALINE GONCALO " number="3025" firstname="" lastname="" phone="" mobile="" email="" address="" city="" state="" zip="" comment="" id="" info="Ready" presence="1" directory="1"/>
<contact name="ALYNE SILVA " number="3074" firstname="" lastname="" phone="" mobile="" email="" address="" city="" state="" zip="" comment="" id="" info="Ready" presence="1" directory="1"/>
<contact name="ANA LUCIA " number="3006" firstname="" lastname="" phone="" mobile="" email="" address="" city="" state="" zip="" comment="" id="" info="Ready" presence="1" directory="1"/>
<contact name="BRUNA MELO " number="3008" firstname="" lastname="" phone="" mobile="" email="" address="" city="" state="" zip="" comment="" id="" info="Ready" presence="1" directory="1"/>
<contact name="BRUNO FERNANDES " number="3077" firstname="" lastname="" phone="" mobile="" email="" address="" city="" state="" zip="" comment="" id="" info="Ready" presence="1" directory="1"/>
<contact name="CLAUDERSON LIMA " number="3009" firstname="" lastname="" phone="" mobile="" email="" address="" city="" state="" zip="" comment="" id="" info="Ready" presence="1" directory="1"/>
<contact name="NEYSE FLOR " number="3026" firstname="" lastname="" phone="" mobile="" email="" address="" city="" state="" zip="" comment="" id="" info="Ready" presence="1" directory="1"/>
<contact name="DANIEL OLIVEIRA " number="3113" firstname="" lastname="" phone="" mobile="" email="" address="" city="" state="" zip="" comment="" id="" info="Ready" presence="1" directory="1"/>
<contact name="ELOISA FRANCA " number="3070" firstname="" lastname="" phone="" mobile="" email="" address="" city="" state="" zip="" comment="" id="" info="Not online" presence="1" directory="1"/>
<contact name="ELTON FERNANDES " number="3071" firstname="" lastname="" phone="" mobile="" email="" address="" city="" state="" zip="" comment="" id="" info="Ready" presence="1" directory="1"/>
<contact name="ERIKA ALBUQUERQUE" number="3141" firstname="" lastname="" phone="" mobile="" email="" address="" city="" state="" zip="" comment="" id="" info="Not online" presence="1" directory="0"/>
<contact name="FRANCISCO BATISTA " number="3078" firstname="" lastname="" phone="" mobile="" email="" address="" city="" state="" zip="" comment="" id="" info="Not online" presence="1" directory="1"/>
<contact name="GARDENIA SOUSA " number="3060" firstname="" lastname="" phone="" mobile="" email="" address="" city="" state="" zip="" comment="" id="" info="Ready" presence="1" directory="1"/>
<contact name="GEIZA SILVA " number="3108" firstname="" lastname="" phone="" mobile="" email="" address="" city="" state="" zip="" comment="" id="" info="Ready" presence="1" directory="1"/>
<contact name="HUGO SOARES " number="3072" firstname="" lastname="" phone="" mobile="" email="" address="" city="" state="" zip="" comment="" id="" info="Ready" presence="1" directory="1"/>
<contact name="IVANIZE CORTEZ " number="3123" firstname="" lastname="" phone="" mobile="" email="" address="" city="" state="" zip="" comment="" id="" info="Not online" presence="1" directory="1"/>
<contact name="JANISONIA SILVA " number="3024" firstname="" lastname="" phone="" mobile="" email="" address="" city="" state="" zip="" comment="" id="" info="Ready" presence="1" directory="1"/>
<contact name="KIVIA SILVA " number="3151" firstname="" lastname="" phone="" mobile="" email="" address="" city="" state="" zip="" comment="" id="" info="Ready" presence="1" directory="1"/>
<contact name="JOSE BENTO " number="3135" firstname="" lastname="" phone="" mobile="" email="" address="" city="" state="" zip="" comment="" id="" info="Ready" presence="1" directory="1"/>
<contact name="KELLY SOUZA " number="3061" firstname="" lastname="" phone="" mobile="" email="" address="" city="" state="" zip="" comment="" id="" info="Ready" presence="1" directory="1"/>
<contact name="ANA LARISSA " number="3023" firstname="" lastname="" phone="" mobile="" email="" address="" city="" state="" zip="" comment="" id="" info="Ready" presence="1" directory="1"/>
<contact name="MADJO CASSIANO " number="3125" firstname="" lastname="" phone="" mobile="" email="" address="" city="" state="" zip="" comment="" id="" info="Ready" presence="1" directory="1"/>
<contact name="MARIA OLIVEIRA " number="3063" firstname="" lastname="" phone="" mobile="" email="" address="" city="" state="" zip="" comment="" id="" info="Ready" presence="1" directory="1"/>
<contact name="MARIANA CRUZ " number="3100" firstname="" lastname="" phone="" mobile="" email="" address="" city="" state="" zip="" comment="" id="" info="Not online" presence="1" directory="1"/>
<contact name="MATHEUS CAMARA " number="3116" firstname="" lastname="" phone="" mobile="" email="" address="" city="" state="" zip="" comment="" id="" info="Not online" presence="1" directory="1"/>
<contact name="MONIQUE ZUZA " number="3032" firstname="" lastname="" phone="" mobile="" email="" address="" city="" state="" zip="" comment="" id="" info="Ready" presence="1" directory="1"/>
<contact name="NADSON XAVIER " number="3027" firstname="" lastname="" phone="" mobile="" email="" address="" city="" state="" zip="" comment="" id="" info="Ready" presence="1" directory="1"/>
<contact name="NATALIA DINA " number="3065" firstname="" lastname="" phone="" mobile="" email="" address="" city="" state="" zip="" comment="" id="" info="Ready" presence="1" directory="1"/>
<contact name="MICHELLE ABREU " number="3033" firstname="" lastname="" phone="" mobile="" email="" address="" city="" state="" zip="" comment="" id="" info="Ready" presence="1" directory="1"/>
<contact name="RAFAELA MELO " number="3019" firstname="" lastname="" phone="" mobile="" email="" address="" city="" state="" zip="" comment="" id="" info="On the phone" presence="1" directory="1"/>
<contact name="RAUL BEZERRA " number="3036" firstname="" lastname="" phone="" mobile="" email="" address="" city="" state="" zip="" comment="" id="" info="Not online" presence="1" directory="1"/>
<contact name="*GN RECEPCAO " number="3001" firstname="" lastname="" phone="" mobile="" email="" address="" city="" state="" zip="" comment="" id="" info="Ready" presence="1" directory="1"/>
<contact name="RENATA SILVA " number="3046" firstname="" lastname="" phone="" mobile="" email="" address="" city="" state="" zip="" comment="" id="" info="Not online" presence="1" directory="1"/>
<contact name="JOCELIA ROCHA " number="3017" firstname="" lastname="" phone="" mobile="" email="" address="" city="" state="" zip="" comment="" id="" info="Ready" presence="1" directory="1"/>
<contact name="ROSEANE SOUZA " number="3047" firstname="" lastname="" phone="" mobile="" email="" address="" city="" state="" zip="" comment="" id="" info="Ready" presence="1" directory="1"/>
<contact name="SAMARA SILVA " number="3049" firstname="" lastname="" phone="" mobile="" email="" address="" city="" state="" zip="" comment="" id="" info="Not online" presence="1" directory="1"/>
<contact name="SAMILA COSTA " number="3090" firstname="" lastname="" phone="" mobile="" email="" address="" city="" state="" zip="" comment="" id="" info="Not online" presence="1" directory="1"/>
<contact name="SANDRILEIA DUTRA " number="3050" firstname="" lastname="" phone="" mobile="" email="" address="" city="" state="" zip="" comment="" id="" info="Not online" presence="1" directory="1"/>
<contact name="*GN MONITORAMENTO " number="3109" firstname="" lastname="" phone="" mobile="" email="" address="" city="" state="" zip="" comment="" id="" info="Not online" presence="1" directory="1"/>
<contact name="WAGNER CRUZ " number="3107" firstname="" lastname="" phone="" mobile="" email="" address="" city="" state="" zip="" comment="" id="" info="Ready" presence="1" directory="1"/>
<contact name="EDWELTON LIMA " number="3160" firstname="" lastname="" phone="" mobile="" email="" address="" city="" state="" zip="" comment="" id="" info="Ready" presence="1" directory="1"/>  
<contact name="RAFAELLA PAZ " number="3073" firstname="" lastname="" phone="" mobile="" email="" address="" city="" state="" zip="" comment="" id="" info="Ready" presence="1" directory="1"/>
<contact name="RODRIGO MOURA " number="3144" firstname="" lastname="" phone="" mobile="" email="" address="" city="" state="" zip="" comment="" id="" info="Ready" presence="1" directory="1"/>
<contact name="HANNIEL CAMARA" number="3087" firstname="" lastname="" phone="" mobile="" email="" address="" city="" state="" zip="" comment="" id="" info="Not online" presence="1" directory="1"/>
<contact name="CLEBIO GOMES" number="3053" firstname="" lastname="" phone="" mobile="" email="" address="" city="" state="" zip="" comment="" id="" info="Not online" presence="1" directory="1"/>
<contact name="LARISSA BATISTA" number="3142" firstname="" lastname="" phone="" mobile="" email="" address="" city="" state="" zip="" comment="" id="" info="Not online" presence="1" directory="1"/>
<contact name="MAYARA DANTAS" number="3157" firstname="" lastname="" phone="" mobile="" email="" address="" city="" state="" zip="" comment="" id="" info="Not online" presence="1" directory="1"/>
<contact name="JOSE ROBERTO " number="3164" firstname="" lastname="" phone="" mobile="" email="" address="" city="" state="" zip="" comment="" id="" info="Not online" presence="1" directory="1"/>
<contact name="POEMA SANTOS" number="3165" firstname="" lastname="" phone="" mobile="" email="" address="" city="" state="" zip="" comment="" id="" info="Not online" presence="1" directory="1"/>
<contact name="EDSON MOURA" number="3121" firstname="" lastname="" phone="" mobile="" email="" address="" city="" state="" zip="" comment="" id="" info="Not online" presence="1" directory="1"/>

</contacts>

<!-- Antigos colaboradores que não foram migrados para a central gentilnegocios.ipxtelecom 

<contact name="AISSA CAVALCANTI" number="3055" firstname="" lastname="" phone="" mobile="" email="" address="" city="" state="" zip="" comment="" id="" info="Not online" presence="1" directory="1"/>
<contact name="ALEXANDRE DEMENDI " number="3106" firstname="" lastname="" phone="" mobile="" email="" address="" city="" state="" zip="" comment="" id="" info="Not online" presence="1" directory="1"/>
<contact name="ALLYSON SILVA " number="3128" firstname="" lastname="" phone="" mobile="" email="" address="" city="" state="" zip="" comment="" id="" info="Not online" presence="1" directory="1"/>
<contact name="ALYNE AQUINO " number="3021" firstname="" lastname="" phone="" mobile="" email="" address="" city="" state="" zip="" comment="" id="" info="Ready" presence="1" directory="1"/>
<contact name="ANTONIA SILVA " number="3136" firstname="" lastname="" phone="" mobile="" email="" address="" city="" state="" zip="" comment="" id="" info="Not online" presence="1" directory="1"/>
<contact name="ANTONIO GENTIL " number="3007" firstname="" lastname="" phone="" mobile="" email="" address="" city="" state="" zip="" comment="" id="" info="Not online" presence="1" directory="1"/>
<contact name="BEATRIZ SANTOS " number="3091" firstname="" lastname="" phone="" mobile="" email="" address="" city="" state="" zip="" comment="" id="" info="Not online" presence="1" directory="1"/>
<contact name="BRUNO SOUZA " number="3079" firstname="" lastname="" phone="" mobile="" email="" address="" city="" state="" zip="" comment="" id="" info="Not online" presence="1" directory="1"/>
<contact name="CAMILA GOMES " number="3114" firstname="" lastname="" phone="" mobile="" email="" address="" city="" state="" zip="" comment="" id="" info="Not online" presence="1" directory="1"/>
<contact name="CAMILA GOUVEIA " number="3131" firstname="" lastname="" phone="" mobile="" email="" address="" city="" state="" zip="" comment="" id="" info="Ready" presence="1" directory="1"/>
<contact name="CLARISSA MARINHO " number="3080" firstname="" lastname="" phone="" mobile="" email="" address="" city="" state="" zip="" comment="" id="" info="Not online" presence="1" directory="1"/>
<contact name="MAURISERGIO DIAS " number="3150" firstname="" lastname="" phone="" mobile="" email="" address="" city="" state="" zip="" comment="" id="" info="Not online" presence="1" directory="1"/>
<contact name="KALLYNE BEZERRA " number="3148" firstname="" lastname="" phone="" mobile="" email="" address="" city="" state="" zip="" comment="" id="" info="Ready" presence="1" directory="1"/>
<contact name="ELAINE SANTOS " number="3011" firstname="" lastname="" phone="" mobile="" email="" address="" city="" state="" zip="" comment="" id="" info="Ready" presence="1" directory="1"/>
<contact name="ELISON SILVA " number="3068" firstname="" lastname="" phone="" mobile="" email="" address="" city="" state="" zip="" comment="" id="" info="Not online" presence="1" directory="1"/>
<contact name="ENILSON SILVA " number="3134" firstname="" lastname="" phone="" mobile="" email="" address="" city="" state="" zip="" comment="" id="" info="Not online" presence="1" directory="1"/>
<contact name="FERNANDO NETO " number="3086" firstname="" lastname="" phone="" mobile="" email="" address="" city="" state="" zip="" comment="" id="" info="Not online" presence="1" directory="1"/>
<contact name="FILIPI GENTIL " number="3003" firstname="" lastname="" phone="" mobile="" email="" address="" city="" state="" zip="" comment="" id="" info="Not online" presence="1" directory="1"/>
<contact name="GABRIEL COUTINHO " number="3089" firstname="" lastname="" phone="" mobile="" email="" address="" city="" state="" zip="" comment="" id="" info="Not online" presence="1" directory="1"/>
<contact name="GIOVANA DINIZ " number="7084" firstname="" lastname="" phone="" mobile="" email="" address="" city="" state="" zip="" comment="" id="" info="Not online" presence="1" directory="1"/>
<contact name="GLAUBER GENTIL " number="3002" firstname="" lastname="" phone="" mobile="" email="" address="" city="" state="" zip="" comment="" id="" info="Not online" presence="1" directory="1"/>
<contact name="GLAUCIO TEIXEIRA " number="3005" firstname="" lastname="" phone="" mobile="" email="" address="" city="" state="" zip="" comment="" id="" info="Not online" presence="1" directory="1"/>
<contact name="GRACO SILVA " number="3119" firstname="" lastname="" phone="" mobile="" email="" address="" city="" state="" zip="" comment="" id="" info="Ready" presence="1" directory="1"/>
<contact name="GUILHERME AMARAL " number="3088" firstname="" lastname="" phone="" mobile="" email="" address="" city="" state="" zip="" comment="" id="" info="Ready" presence="1" directory="1"/>
<contact name="GUILHERME EMERECIANO " number="3056" firstname="" lastname="" phone="" mobile="" email="" address="" city="" state="" zip="" comment="" id="" info="Ready" presence="1" directory="1"/>
<contact name="HENRIQUE MEDEIROS " number="3105" firstname="" lastname="" phone="" mobile="" email="" address="" city="" state="" zip="" comment="" id="" info="Not online" presence="1" directory="1"/>
<contact name="HUGO SLZ SEGURANCA " number="7081" firstname="" lastname="" phone="" mobile="" email="" address="" city="" state="" zip="" comment="" id="" info="Not online" presence="1" directory="1"/>
<contact name="INSTITUTO GENTIL " number="8001" firstname="" lastname="" phone="" mobile="" email="" address="" city="" state="" zip="" comment="" id="" info="Not online" presence="1" directory="1"/>
<contact name="ISLA QUEIROZ " number="3037" firstname="" lastname="" phone="" mobile="" email="" address="" city="" state="" zip="" comment="" id="" info="Ready" presence="1" directory="1"/>
<contact name="ITALO SOUZA " number="3052" firstname="" lastname="" phone="" mobile="" email="" address="" city="" state="" zip="" comment="" id="" info="Ready" presence="1" directory="1"/>
<contact name="JOYCE OLIVEIRA " number="3092" firstname="" lastname="" phone="" mobile="" email="" address="" city="" state="" zip="" comment="" id="" info="Not online" presence="1" directory="1"/>
<contact name="JOYCE OLIVEIRA " number="3118" firstname="" lastname="" phone="" mobile="" email="" address="" city="" state="" zip="" comment="" id="" info="Ready" presence="1" directory="1"/>
<contact name="JOAO FERNANDES " number="3067" firstname="" lastname="" phone="" mobile="" email="" address="" city="" state="" zip="" comment="" id="" info="Ready" presence="1" directory="1"/>
<contact name="JOAO OLIVEIRA " number="3022" firstname="" lastname="" phone="" mobile="" email="" address="" city="" state="" zip="" comment="" id="" info="Not online" presence="1" directory="1"/>
<contact name="JUSDEANNY NASCIMENTO " number="3038" firstname="" lastname="" phone="" mobile="" email="" address="" city="" state="" zip="" comment="" id="" info="Ready" presence="1" directory="1"/>
<contact name="KARLA SILVA " number="3035" firstname="" lastname="" phone="" mobile="" email="" address="" city="" state="" zip="" comment="" id="" info="Ready" presence="1" directory="1"/>
<contact name="KLEYTHON ROCHA " number="3133" firstname="" lastname="" phone="" mobile="" email="" address="" city="" state="" zip="" comment="" id="" info="Not online" presence="1" directory="1"/>
<contact name="LAYS NASCIMENTO " number="3039" firstname="" lastname="" phone="" mobile="" email="" address="" city="" state="" zip="" comment="" id="" info="Not online" presence="1" directory="1"/>
<contact name="LIALYSON LOPES " number="3031" firstname="" lastname="" phone="" mobile="" email="" address="" city="" state="" zip="" comment="" id="" info="Ready" presence="1" directory="1"/>
<contact name="LIDIANE SANTOS " number="7080" firstname="" lastname="" phone="" mobile="" email="" address="" city="" state="" zip="" comment="" id="" info="Ready" presence="1" directory="1"/>
<contact name="LIVIA DANTAS " number="3014" firstname="" lastname="" phone="" mobile="" email="" address="" city="" state="" zip="" comment="" id="" info="Ready" presence="1" directory="1"/>
<contact name="LORENA SILVA " number="3130" firstname="" lastname="" phone="" mobile="" email="" address="" city="" state="" zip="" comment="" id="" info="Not online" presence="1" directory="1"/>
<contact name="LUANA RAFAELA " number="3016" firstname="" lastname="" phone="" mobile="" email="" address="" city="" state="" zip="" comment="" id="" info="Ready" presence="1" directory="1"/>
<contact name="MANOEL FREIRE " number="3127" firstname="" lastname="" phone="" mobile="" email="" address="" city="" state="" zip="" comment="" id="" info="Not online" presence="1" directory="1"/>
<contact name="MARIA CLARA " number="3082" firstname="" lastname="" phone="" mobile="" email="" address="" city="" state="" zip="" comment="" id="" info="Not online" presence="1" directory="1"/>
<contact name="MARIA LIMA " number="3137" firstname="" lastname="" phone="" mobile="" email="" address="" city="" state="" zip="" comment="" id="" info="Not online" presence="1" directory="1"/>
<contact name="MAYCO BRAGA " number="7083" firstname="" lastname="" phone="" mobile="" email="" address="" city="" state="" zip="" comment="" id="" info="Not online" presence="1" directory="1"/>
<contact name="MERIENE ARAUJO " number="3064" firstname="" lastname="" phone="" mobile="" email="" address="" city="" state="" zip="" comment="" id="" info="Ready" presence="1" directory="1"/>
<contact name="MONITORAMENTO2 " number="3111" firstname="" lastname="" phone="" mobile="" email="" address="" city="" state="" zip="" comment="" id="" info="Not online" presence="1" directory="1"/>
<contact name="PEDRO ALVES " number="3117" firstname="" lastname="" phone="" mobile="" email="" address="" city="" state="" zip="" comment="" id="" info="Not online" presence="1" directory="1"/>
<contact name="PEDRO GALVAO " number="3099" firstname="" lastname="" phone="" mobile="" email="" address="" city="" state="" zip="" comment="" id="" info="Ready" presence="1" directory="1"/>
<contact name="RAFAEL MORETTI " number="3096" firstname="" lastname="" phone="" mobile="" email="" address="" city="" state="" zip="" comment="" id="" info="Not online" presence="1" directory="1"/>
<contact name="RAQUEL SOUZA " number="3045" firstname="" lastname="" phone="" mobile="" email="" address="" city="" state="" zip="" comment="" id="" info="Ready" presence="1" directory="1"/>
<contact name="RAUL MOREIRA " number="3098" firstname="" lastname="" phone="" mobile="" email="" address="" city="" state="" zip="" comment="" id="" info="Not online" presence="1" directory="1"/>
<contact name="RAVENA NUNES " number="3029" firstname="" lastname="" phone="" mobile="" email="" address="" city="" state="" zip="" comment="" id="" info="Ready" presence="1" directory="1"/>
<contact name="REGIANE TEIXEIRA " number="3066" firstname="" lastname="" phone="" mobile="" email="" address="" city="" state="" zip="" comment="" id="" info="Ready" presence="1" directory="1"/>
<contact name="RENATO LUCAS " number="3093" firstname="" lastname="" phone="" mobile="" email="" address="" city="" state="" zip="" comment="" id="" info="Ready" presence="1" directory="1"/>
<contact name="STEFFANY RAMOS " number="3083" firstname="" lastname="" phone="" mobile="" email="" address="" city="" state="" zip="" comment="" id="" info="Not online" presence="1" directory="1"/>
<contact name="SULAMITA SILVA " number="3018" firstname="" lastname="" phone="" mobile="" email="" address="" city="" state="" zip="" comment="" id="" info="Ready" presence="1" directory="1"/>
<contact name="TALLITA ELLEN " number="3044" firstname="" lastname="" phone="" mobile="" email="" address="" city="" state="" zip="" comment="" id="" info="Not online" presence="1" directory="1"/>
<contact name="TAYANE VARELA " number="3059" firstname="" lastname="" phone="" mobile="" email="" address="" city="" state="" zip="" comment="" id="" info="Ready" presence="1" directory="1"/>
<contact name="TERCIA NETA " number="3051" firstname="" lastname="" phone="" mobile="" email="" address="" city="" state="" zip="" comment="" id="" info="Not online" presence="1" directory="1"/>
<contact name="THAIS SOARES " number="3129" firstname="" lastname="" phone="" mobile="" email="" address="" city="" state="" zip="" comment="" id="" info="Not online" presence="1" directory="1"/>
<contact name="THIAGO SOUZA " number="3103" firstname="" lastname="" phone="" mobile="" email="" address="" city="" state="" zip="" comment="" id="" info="Ready" presence="1" directory="1"/>
<contact name="TIAGO PEREIRA " number="3120" firstname="" lastname="" phone="" mobile="" email="" address="" city="" state="" zip="" comment="" id="" info="Not online" presence="1" directory="1"/>
<contact name="VINICIUS SILVA " number="3041" firstname="" lastname="" phone="" mobile="" email="" address="" city="" state="" zip="" comment="" id="" info="Ready" presence="1" directory="1"/>
<contact name="CINTHIA CARIDADE " number="3149" firstname="" lastname="" phone="" mobile="" email="" address="" city="" state="" zip="" comment="" id="" info="Ready" presence="1" directory="1"/>


-->
